examples/__init__.py
examples/enroll_email_factor.py
examples/enroll_google_auth_factor.py
examples/enroll_okta_otp_factor.py
examples/enroll_okta_push_factor.py
examples/enroll_question_factor.py
examples/enroll_sms_factor.py
examples/enroll_voice_call_factor.py
examples/okta_class_extensions.py
examples/script_config.py
examples/user_operations.py
examples/users_search.py
examples/verify_email_factor.py
examples/verify_google_auth_factor.py
examples/verify_okta_otp_factor.py
examples/verify_okta_push_factor.py
examples/verify_question_factor.py
examples/verify_sms_factor.py
examples/verify_voice_call_factor.py
okta/AppInstanceClient.py
okta/AuthClient.py
okta/EventsClient.py
okta/FactorsAdminClient.py
okta/FactorsClient.py
okta/SessionsClient.py
okta/UserGroupsClient.py
okta/UsersClient.py
okta/__init__.py
okta/__version__.py
okta/framework/ApiClient.py
okta/framework/Deserializer.py
okta/framework/OktaError.py
okta/framework/PagedResults.py
okta/framework/Serializer.py
okta/framework/Utils.py
okta/framework/__init__.py
okta/models/Embedded.py
okta/models/Link.py
okta/models/__init__.py
okta/models/app/Accessibility.py
okta/models/app/AppCredentials.py
okta/models/app/AppGroup.py
okta/models/app/AppInstance.py
okta/models/app/AppLinks.py
okta/models/app/AppSettings.py
okta/models/app/AppUser.py
okta/models/app/AppUserCredentials.py
okta/models/app/AppUserProfile.py
okta/models/app/Hide.py
okta/models/app/Settings.py
okta/models/app/UserNameTemplate.py
okta/models/app/Visibility.py
okta/models/app/__init__.py
okta/models/auth/AuthResult.py
okta/models/auth/__init__.py
okta/models/event/Action.py
okta/models/event/Actor.py
okta/models/event/Event.py
okta/models/event/Target.py
okta/models/event/__init__.py
okta/models/factor/ActivationResponse.py
okta/models/factor/Factor.py
okta/models/factor/FactorCatalogEntry.py
okta/models/factor/FactorDevice.py
okta/models/factor/FactorDeviceEnrollRequest.py
okta/models/factor/FactorDeviceRequest.py
okta_sdk_python-0.2.1.dist-info/LICENSE
okta_sdk_python-0.2.1.dist-info/LICENSE.txt
okta_sdk_python-0.2.1.dist-info/METADATA
okta_sdk_python-0.2.1.dist-info/WHEEL
okta_sdk_python-0.2.1.dist-info/top_level.txt
okta_sdk_python-0.2.1.dist-info/RECORD
