Metadata-Version: 2.1
Name: okta-sdk-python
Version: 0.2.1
Summary: Okta management SDK for Python. Forked from https://github.com/okta/okta-sdk-python.
Home-page: https://github.com/mdwallick/okta-sdk-python
Author: Mike Wallick
Author-email: mike@wallick.net
License: Apache License 2.0
Platform: UNKNOWN
Classifier: Development Status :: 4 - Beta
Classifier: Intended Audience :: Developers
Classifier: Programming Language :: Python
Classifier: Programming Language :: Python :: 2
Classifier: Programming Language :: Python :: 2.7
Classifier: Programming Language :: Python :: 3
Classifier: Programming Language :: Python :: 3.7
Classifier: License :: OSI Approved :: Apache Software License
Requires-Python: >=2.7.0
Requires-Dist: requests (>=2.23.0)
Requires-Dist: python-dateutil (>=2.8.1)
Requires-Dist: six (>=1.15.0)
